flatiron/__init__.py
flatiron/api.py
flatiron/command.py
flatiron/core/__init__.py
flatiron/core/config.py
flatiron/core/dataset.py
flatiron/core/logging.py
flatiron/core/multidataset.py
flatiron/core/pipeline.py
flatiron/core/resolve.py
flatiron/core/tools.py
flatiron/core/types.py
flatiron/core/validators.py
flatiron/py.typed
flatiron/tf/__init__.py
flatiron/tf/config.py
flatiron/tf/loss.py
flatiron/tf/metric.py
flatiron/tf/models/__init__.py
flatiron/tf/models/dummy.py
flatiron/tf/models/unet.py
flatiron/tf/optimizer.py
flatiron/tf/tools.py
flatiron/torch/__init__.py
flatiron/torch/config.py
flatiron/torch/loss.py
flatiron/torch/metric.py
flatiron/torch/models/__init__.py
flatiron/torch/models/dummy.py
flatiron/torch/models/unet.py
flatiron/torch/optimizer.py
flatiron/torch/tools.py
flatiron-0.26.0.dist-info/entry_points.txt
flatiron-0.26.0.dist-info/WHEEL
flatiron-0.26.0.dist-info/METADATA
flatiron-0.26.0.dist-info/licenses/LICENSE
flatiron-0.26.0.dist-info/RECORD
