Metadata-Version: 2.1
Name: flatiron
Version: 0.26.0
Summary: Standardized computer vision pipeline framework with a chainable API and procedurally defined model architecture.
License: MIT
Keywords: unet,tensorflow,artificial intelligence,artificial-intelligence,cnn,computer vision,computer-vision,deep learning,deep-learning,machine learning,machine-learning
Author-email: Alex Braun <alexander.g.braun@gmail.com>
Requires-Python: >=3.10
Classifier: Development Status :: 4 - Beta
Classifier: Intended Audience :: Developers
Classifier: License :: OSI Approved :: MIT License
Classifier: Programming Language :: Python :: 3
Classifier: Programming Language :: Python :: 3.10
Classifier: Programming Language :: Python :: 3.11
Classifier: Programming Language :: Python :: 3.12
Classifier: Typing :: Typed
Requires-Dist: click>=8.1.3
Requires-Dist: cv-depot>=0.10.2
Requires-Dist: humanfriendly
Requires-Dist: lunchbox>=0.3.3
Requires-Dist: numpy>=2.0.2
Requires-Dist: pandas
Requires-Dist: pydantic>=2.10.6
Requires-Dist: pytz>=2022.7.1
Requires-Dist: pyyaml>=6.0
Requires-Dist: safetensors>=0.5.2
Requires-Dist: tensorboard>=2.0.0
Requires-Dist: tqdm>=4.64.1
Provides-Extra: all
Requires-Dist: tensorflow>=2.18.0; extra == "all"
Requires-Dist: torch; extra == "all"
Requires-Dist: torchmetrics>=1.6.1; extra == "all"
Requires-Dist: torchvision; extra == "all"
Provides-Extra: tensorflow
Requires-Dist: tensorflow>=2.18.0; extra == "tensorflow"
Provides-Extra: torch
Requires-Dist: torch; extra == "torch"
Requires-Dist: torchmetrics>=1.6.1; extra == "torch"
Requires-Dist: torchvision; extra == "torch"
Project-URL: documentation, https://theNewFlesh.github.io/flatiron
Project-URL: repository, https://github.com/thenewflesh/flatiron
